[{"s": "12-motochasov-eto-skolko-kilometrov", "t": "12 моточасов — сколько это километров? Точный расчёт для авто", "i": "🔧", "c": "remont-dvigatelya"}, {"s": "1251-statya-gibdd-shtrafy-tyuning", "t": "Штрафы за тюнинг по ст. 12.5.1 КоАП в 2026: что запрещено и как избежать наказания", "i": "⚖️", "c": "zakony-i-shtrafy"}, {"s": "120-gramm-vodki-cherez-skolko-vyvoditsya-iz-organizma", "t": "120 грамм водки: через сколько выводится из организма водителя?", "i": "🚑", "c": "bezopasnost-i-zdorove"}, {"s": "120-oborotov-v-minutu-skolko-eto-oborotov-v-sekundu", "t": "120 оборотов в минуту — сколько это в секунду? Формула и примеры", "i": "🔧", "c": "remont-dvigatelya"}, {"s": "12-volt-v-9-volt", "t": "Как понизить 12В до 9В в авто: 5 проверенных способов", "i": "⚡", "c": "elektrika-i-svet"}, {"s": "120-km-eto-skolko-chasov", "t": "120 км на машине — сколько это часов езды в 2026 году?", "i": "🗺️", "c": "puteshestviya-i-dorogi"}, {"s": "121-oshibka-chasov-shtrikh-kak-ustranit", "t": "Ошибка 121 на часах Штрих: причины и 5 способов устранения", "i": "⚡", "c": "elektrika-i-svet"}, {"s": "12v-air-compressor-avtomobilnyj", "t": "12V автокомпрессор: как выбрать, подключить и обслуживать", "i": "🛠️", "c": "aksessuary-i-tyuning"}, {"s": "120-motochasov-eto-skolko-kilometrov", "t": "120 моточасов — сколько это километров? Точный расчёт для авто", "i": "🔧", "c": "remont-dvigatelya"}, {"s": "12-15-psi-skolko-atmosfer", "t": "12 и 15 PSI: перевод в атмосферы для шин", "i": "🧼", "c": "ukhod-i-mojka"}, {"s": "120-km-eto-skolko-po-vremeni-na-mashine-ekhat", "t": "120 км на машине: сколько ехать времени по разным дорогам", "i": "🗺️", "c": "puteshestviya-i-dorogi"}, {"s": "12-v-220-volt-avtomobilnyj-invertor", "t": "12 в 220 вольт автомобильный инвертор: выбор и установка", "i": "🛠️", "c": "aksessuary-i-tyuning"}, {"s": "120-km-v-chas-v-metry-v-sekundu-perevesti", "t": "120 км/ч в м/с: точный перевод и формулы для авто", "i": "⚖️", "c": "zakony-i-shtrafy"}, {"s": "125-gradusov-po-farengejtu-v-tselsiyakh", "t": "125 градусов по Фаренгейту в Цельсиях: точный перевод и таблица", "i": "📁", "c": "drugoe"}, {"s": "125-motochasov-eto-v-kilometrakh", "t": "125 моточасов это сколько км? Точный расчет", "i": "🧼", "c": "ukhod-i-mojka"}, {"s": "120km-v-chas-v-metry-v-sekundu", "t": "120 км/ч в м/с: точный перевод и формулы", "i": "⚖️", "c": "zakony-i-shtrafy"}, {"s": "125-m-s-v-km-ch", "t": "12.5 м/с в км/ч: быстрый перевод и таблица", "i": "🗺️", "c": "puteshestviya-i-dorogi"}, {"s": "120m-v-sekundu-skolko-km-v-chas", "t": "120 м/с в км/ч: перевод скорости и таблицы для авто", "i": "📁", "c": "drugoe"}, {"s": "12-km-v-chas-v-metry-v-sekundu", "t": "12 км/ч в м/с: перевод и таблица скоростей для авто", "i": "📁", "c": "drugoe"}, {"s": "125-psi-skolko-atmosfer", "t": "125 psi сколько атмосфер: точный перевод давления в шинах", "i": "🧼", "c": "ukhod-i-mojka"}, {"s": "1200-km-eto-skolko-po-vremeni", "t": "1200 км: сколько ехать на машине, автобусе и поезде", "i": "🗺️", "c": "puteshestviya-i-dorogi"}, {"s": "120-m-v-sekundu-skolko-km-v-chas", "t": "120 м в секунду сколько км в час: точный расчет скорости", "i": "📁", "c": "drugoe"}, {"s": "12-ls-v-km-ch", "t": "12 лс в км ч: конвертация мощности и скорости авто", "i": "📁", "c": "drugoe"}, {"s": "12000-km-v-chas-v-metrakh-v-sekundu", "t": "12000 км/ч в м/с: точный расчет и влияние на авто", "i": "🗺️", "c": "puteshestviya-i-dorogi"}, {"s": "120-zl-v-rublyakh", "t": "120 zl в рублях: актуальный курс и где выгоднее менять", "i": "🗺️", "c": "puteshestviya-i-dorogi"}, {"s": "126-km-skolko-po-vremeni-ekhat-na-mashine", "t": "126 км на машине: сколько ехать по времени и тратам", "i": "🗺️", "c": "puteshestviya-i-dorogi"}, {"s": "122-chej-region-avtomobilnyj", "t": "122 регион: какой город и что означает код", "i": "📄", "c": "registratsiya-i-dokumenty"}, {"s": "128-km-v-chas-v-metry-v-sekundu", "t": "128 км/ч в м/с: точный перевод и формула расчета", "i": "🚑", "c": "bezopasnost-i-zdorove"}, {"s": "12-5-2-statya-gibdd", "t": "Статья 12.5.2 КоАП РФ: штраф за отсутствие ОСАГО", "i": "⚖️", "c": "zakony-i-shtrafy"}]