[{"s": "bilet-22-vopros-17-pdd", "t": "Билет 22 вопрос 17 ПДД 2026: разбор с пояснениями и лайфхаками", "i": "⚖️", "c": "zakony-i-shtrafy"}, {"s": "bik-avto-dovatora-7", "t": "БИК авто Доватора-7: расшифровка, проверка и особенности 2026 года", "i": "📄", "c": "registratsiya-i-dokumenty"}, {"s": "bih-nomera-kakoj-strany", "t": "BIH номера: какой стране принадлежат? Полный гайд по автомобильным кодам", "i": "📄", "c": "registratsiya-i-dokumenty"}, {"s": "biznes-idei-s-minimalnymi-vlozheniyami-v-malenkom-gorode-dlya-muzhchin-v-garazhe", "t": "Бизнес в гараже: 15 идей с минимальными вложениями для мужчин в 2026", "i": "🏠", "c": "garazh-i-instrument"}, {"s": "biznes-plan-po-otkrytiyu-sto", "t": "Бизнес-план СТО 2026: расчёты, документы и шаги к прибыли", "i": "🏠", "c": "garazh-i-instrument"}, {"s": "bik-avto-azov-telefon-nomer", "t": "БИК Авто в Азове: официальные телефоны и контакты 2026", "i": "🤝", "c": "pokupka-i-prodazha"}, {"s": "biznes-na-assenizatorskoj-mashine-minusy-i-plyusy", "t": "Бизнес на ассенизаторской машине: плюсы и минусы (2026)", "i": "🤝", "c": "pokupka-i-prodazha"}, {"s": "biznes-na-khimchistke-avto", "t": "Бизнес на химчистке авто: как открыть с нуля и заработать в 2026 году", "i": "🧼", "c": "ukhod-i-mojka"}, {"s": "biznes-v-garazhe-dlya-zhenshchin", "t": "Бизнес в гараже для женщин: 10 идей с нуля и без вложений", "i": "🏠", "c": "garazh-i-instrument"}, {"s": "bilet-30-vopros-15", "t": "Билет 30 вопрос 15 ПДД 2026: разбор сложного момента с разметкой и знаками", "i": "⚖️", "c": "zakony-i-shtrafy"}, {"s": "bilet-31-vopros-17-pdd", "t": "Билет 31 вопрос 17 ПДД 2026: разбор с пояснениями и лайфхаками", "i": "⚖️", "c": "zakony-i-shtrafy"}, {"s": "bibika-ru-avtomobili-s-probegom", "t": "Bibika.ru: как купить автомобиль с пробегом без рисков в 2026 году", "i": "🤝", "c": "pokupka-i-prodazha"}, {"s": "biznes-na-zaryadke-elektromobilej", "t": "Бизнес на зарядке электромобилей: как заработать с нуля в 2026 году", "i": "🤝", "c": "pokupka-i-prodazha"}, {"s": "bi-uaj-di-avtomobil", "t": "BWD автомобиль: что это, как расшифровывается и где применяется", "i": "🤝", "c": "pokupka-i-prodazha"}, {"s": "biznes-klass-eto-kakoj-klass-avtomobilya", "t": "Бизнес-класс автомобиля: что это, отличия от других классов", "i": "🤝", "c": "pokupka-i-prodazha"}, {"s": "bik-avto-tekucheva-42", "t": "БИК Авто Текучева 42: адрес, услуги и отзывы в 2026 году", "i": "🔧", "c": "remont-dvigatelya"}, {"s": "biznes-na-kupi-prodaj", "t": "Бизнес на «купи-продай» авто: с нуля до 500 000 ₽/мес в 2026", "i": "🤝", "c": "pokupka-i-prodazha"}, {"s": "bilet-9-vopros-19", "t": "Билет 9 вопрос 19 ПДД 2026: разбор сложного момента с разворотом", "i": "⚖️", "c": "zakony-i-shtrafy"}, {"s": "bibikane-mashiny-kak-nazyvaetsya", "t": "Бибиканье машины: как правильно называется и что означает?", "i": "🚑", "c": "bezopasnost-i-zdorove"}, {"s": "biled-linzy-dlya-avtomobilnykh-far-kupit", "t": "Билед-линзы для фар: как выбрать и где купить в 2026 году", "i": "🛠️", "c": "aksessuary-i-tyuning"}, {"s": "biznes-fm-piter-chastota", "t": "Бизнес FM в Питере: частота вещания и как настроить в 2026 году", "i": "📁", "c": "drugoe"}, {"s": "biznes-idei-v-garazhe-dlya-muzhchin-s-minimalnymi-vlozheniyami-malenkogo-goroda", "t": "Бизнес в гараже: 12 идей для мужчин с нуля (маленький город)", "i": "🏠", "c": "garazh-i-instrument"}, {"s": "biznes-na-sdache-mashin-v-arendu", "t": "Бизнес на сдаче машин в аренду: старт и риски", "i": "📁", "c": "drugoe"}, {"s": "big-wind-pozharnaya-mashina", "t": "Big Wind: пожарная машина для аэродромов. Характеристики и устройство", "i": "🏠", "c": "garazh-i-instrument"}, {"s": "bilet-10-vopros-13", "t": "Билет 10 Вопрос 13 ПДД: остановка и стоянка, знаки", "i": "⚖️", "c": "zakony-i-shtrafy"}, {"s": "biznes-na-zaryadnykh-stantsiyakh-dlya-elektromobilej", "t": "Бизнес на зарядных станциях для электромобилей: старт и окупаемость", "i": "🛠️", "c": "aksessuary-i-tyuning"}, {"s": "biznes-fm-radio-chastota", "t": "Бизнес ФМ частота: список городов и способы настройки", "i": "🛠️", "c": "aksessuary-i-tyuning"}, {"s": "biak-u-5-plyus", "t": "Биак У5 Плюс: Полный обзор, характеристики и особенности", "i": "🤝", "c": "pokupka-i-prodazha"}, {"s": "billie-eilish-everything-i-wanted-klip", "t": "Billie Eilish Everything I Wanted: анализ клипа и смыслов", "i": "📁", "c": "drugoe"}, {"s": "bienie-koles-na-skorosti-100-120", "t": "Биение колес на скорости 100-120 км/ч: причины, диагностика и устранение", "i": "🔧", "c": "remont-dvigatelya"}, {"s": "biturbirovannyj-dvigatel-chto-eto", "t": "Битурбированный двигатель: что это, как работает и стоит ли покупать", "i": "🔧", "c": "remont-dvigatelya"}, {"s": "biznes-gruzoperevozki-s-chego-nachat-i-plyusy-s-minusom", "t": "Бизнес грузоперевозки с нуля: пошаговый план и анализ", "i": "📁", "c": "drugoe"}, {"s": "bilet-22-vopros-12-pdd", "t": "Билет 22 вопрос 12 ПДД: разбор остановки и стоянки", "i": "⚖️", "c": "zakony-i-shtrafy"}, {"s": "bilet-30-vopros-10-pdd", "t": "Билет 30 вопрос 10 ПДД: правильный ответ и разбор ситуации", "i": "⚖️", "c": "zakony-i-shtrafy"}, {"s": "bipek-avto-aktobe-tseny-na-avto", "t": "Bipek Auto Актобе: актуальные цены на авто и обзор рынка", "i": "🤝", "c": "pokupka-i-prodazha"}, {"s": "biznes-na-sdache-garazhej-v-arendu", "t": "Бизнес на сдаче гаражей в аренду: как заработать и не прогореть", "i": "🏠", "c": "garazh-i-instrument"}, {"s": "biznes-v-garazhe-idei-dlya-muzhchin-proizvodstvo-s-minimalnymi-vlozheniyami", "t": "Бизнес в гараже: идеи для мужчин с минимальными вложениями", "i": "🏠", "c": "garazh-i-instrument"}, {"s": "bilet-platforma-9-i-3-4", "t": "Платформы 3 и 4: где искать поезд на вокзале", "i": "🗺️", "c": "puteshestviya-i-dorogi"}, {"s": "biznes-na-pereprodazhe-avtomobilej", "t": "Бизнес на перепродаже автомобилей: старт, риски и прибыль", "i": "🤝", "c": "pokupka-i-prodazha"}, {"s": "biznes-na-detejlinge-avto", "t": "Бизнес на детейлинге авто: с чего начать и как заработать", "i": "🧼", "c": "ukhod-i-mojka"}, {"s": "biografiya-izobretatelya-applikatora-kuznetsova", "t": "Биография изобретателя аппликатора Кузнецова: история иглотерапии", "i": "🚑", "c": "bezopasnost-i-zdorove"}, {"s": "bi-led-linzy-v-avto-kupit", "t": "Bi-LED линзы в авто купить: выбор, установка и цены 2026", "i": "🛠️", "c": "aksessuary-i-tyuning"}, {"s": "binokulyar-nochnogo-videniya-na-shlem", "t": "Бинокуляр ночного видения на шлем: выбор, крепление и обзор", "i": "🛠️", "c": "aksessuary-i-tyuning"}, {"s": "binder-dlya-pokraski-avto-v-ballonchike", "t": "Биндер для покраски авто: выбор и применение в баллончиках", "i": "🎨", "c": "kuzov-i-okraska"}, {"s": "bisernyj-shov-na-shvejnoj-mashinke", "t": "Бисерный шов на швейной машинке: пошаговая инструкция", "i": "📁", "c": "drugoe"}, {"s": "bilet-40-vopros-5", "t": "Билет 40 вопрос 5 ПДД 2026: Разрешен ли обгон на перекрестке?", "i": "⚖️", "c": "zakony-i-shtrafy"}, {"s": "bistsion-gerb-semi-viskonti", "t": "Бисцион герб семьи Висконти: история и символика", "i": "📁", "c": "drugoe"}, {"s": "bilet-10-vopros-19", "t": "Билет 10 вопрос 19 ПДД 2026: остановка и стоянка", "i": "⚖️", "c": "zakony-i-shtrafy"}, {"s": "bilet-28-vopros-6-pdd", "t": "Билет 28 вопрос 6 ПДД: правильный ответ и пояснение", "i": "⚖️", "c": "zakony-i-shtrafy"}, {"s": "birki-dlya-to-avtomobilya", "t": "Бирки для авто: выбор, виды и правильная маркировка", "i": "🛠️", "c": "aksessuary-i-tyuning"}, {"s": "bilet-22-vopros-8-pdd", "t": "Билет 22 вопрос 8 ПДД: ответ и разбор ситуации", "i": "⚖️", "c": "zakony-i-shtrafy"}, {"s": "bitum-na-mashine-kak-otmyt", "t": "Как отмыть битум с машины: лучшие средства и методы", "i": "📁", "c": null}, {"s": "biznes-na-sdache-avto-v-arendu-v-taksi", "t": "Бизнес на сдаче авто в аренду в такси: старт и риски", "i": "🤝", "c": "pokupka-i-prodazha"}, {"s": "bitumnaya-shumoizolyatsiya-dlya-avto-samokleyushchayasya", "t": "Битумная шумоизоляция для авто самоклеющаяся: выбор и монтаж", "i": "🛠️", "c": "aksessuary-i-tyuning"}, {"s": "bilet-na-platformu-9-i-3-chetverti-iz-garri-pottera", "t": "Билет на платформу 9 и 3 четверти: где купить и как попасть", "i": "📁", "c": "drugoe"}, {"s": "biznes-na-svoem-avtomobile", "t": "Бизнес на своем автомобиле: как начать зарабатывать водителем", "i": "🤝", "c": "pokupka-i-prodazha"}, {"s": "bigfut-iz-filma-nyanki", "t": "Бигфут из фильма Няньки: как собрать автодом своими руками", "i": "🛠️", "c": "aksessuary-i-tyuning"}, {"s": "biotualet-s-elektricheskim-smyvom", "t": "Биотуалет с электрическим смывом: обзор, монтаж и уход", "i": "🛠️", "c": "aksessuary-i-tyuning"}, {"s": "bistun-avtomobil-b-70", "t": "Бестун Б70: обзор кроссовера FAW в кузове седан", "i": "🤝", "c": "pokupka-i-prodazha"}, {"s": "bilet-30-vopros-4", "t": "Билет 30 вопрос 4 ПДД: ответ на экзамене ГИБДД", "i": "⚖️", "c": "zakony-i-shtrafy"}, {"s": "bio-ajdi-kitajskij-avtomobil", "t": "Китайский автомобиль: био айди и его влияние на цену", "i": "🤝", "c": "pokupka-i-prodazha"}, {"s": "biznes-idei-dlya-garazha-svoimi-rukami", "t": "Бизнес идеи для гаража своими руками: ТОП-10 направлений", "i": "🏠", "c": "garazh-i-instrument"}, {"s": "biznes-gruzoperevozki-na-fure", "t": "Бизнес на грузоперевозках: как начать дело на фуре", "i": "🗺️", "c": "puteshestviya-i-dorogi"}, {"s": "biznes-assenizatorskaya-mashina-s-chego-nachat", "t": "Бизнес на ассенизаторской машине: с чего начать новичку", "i": "🤝", "c": "pokupka-i-prodazha"}, {"s": "bitumnyj-lak-ili-mastika", "t": "Битумный лак или мастика: что выбрать для авто и почему", "i": "🧼", "c": "ukhod-i-mojka"}, {"s": "biznes-na-pereprodazhe-garazhej", "t": "Бизнес на перепродаже гаражей: пошаговый план и риски", "i": "🏠", "c": "garazh-i-instrument"}, {"s": "biznes-na-radioupravlyaemykh-mashinkakh", "t": "Бизнес на радиоуправляемых машинках: план запуска и прибыль", "i": "📁", "c": "drugoe"}, {"s": "bilety-po-psikhologii-pdd", "t": "Билеты по психологии ПДД 2026: ответы и разбор", "i": "⚖️", "c": "zakony-i-shtrafy"}, {"s": "bipek-avto-petropavlovsk-tseny", "t": "Бипек Авто Петропавловск: актуальные цены на авто 2026", "i": "🤝", "c": "pokupka-i-prodazha"}, {"s": "biturbo-chto-eto-takoe-prostymi-slovami", "t": "Битурбо: что это такое простыми словами — принцип работы и виды", "i": "🔧", "c": "remont-dvigatelya"}, {"s": "bild-yu-drims-mashina", "t": "Build Your Dreams: Машины BYD для России — обзор, цены, отзывы", "i": "🤝", "c": "pokupka-i-prodazha"}, {"s": "bitumnaya-mastika-dlya-metalla", "t": "Битумная мастика для металла: защита от коррозии, виды и применение", "i": "🏠", "c": "garazh-i-instrument"}, {"s": "biznes-fm-radio-volna-chastota", "t": "Бизнес FM: частота радиоволны в вашем городе", "i": "📁", "c": "drugoe"}, {"s": "biznes-v-garazhe-idei-dlya-muzhchin-proizvodstvo", "t": "Бизнес в гараже: идеи производства для мужчин с нуля", "i": "🏠", "c": "garazh-i-instrument"}, {"s": "bilet-vam-mozhno-prodolzhit-dvizhenie", "t": "Билет вам можно продолжить движение: расшифровка фразы инспектора", "i": "⚖️", "c": "zakony-i-shtrafy"}, {"s": "biznes-avtoservis-vygodno-li", "t": "Бизнес автосервис выгодно ли: расчеты, риски и прибыль", "i": "🏠", "c": "garazh-i-instrument"}, {"s": "bilet-30-vopros-10", "t": "Билет 30 вопрос 10 ПДД: Ответы и разбор для категории B", "i": "⚖️", "c": "zakony-i-shtrafy"}, {"s": "bilet-9-vopros-11", "t": "Билет 9 вопрос 11 ПДД 2026: Ответы и пояснения", "i": "⚖️", "c": "zakony-i-shtrafy"}, {"s": "bilet-40-vopros-13-pdd", "t": "Билет 40 вопрос 13 ПДД 2026: ответ с пояснением и схемой", "i": "⚖️", "c": "zakony-i-shtrafy"}, {"s": "bipek-avto-almaty-tseny", "t": "Бипек Авто Алматы: актуальные цены и условия 2026", "i": "🤝", "c": "pokupka-i-prodazha"}, {"s": "bitye-avto-zdes-korolev", "t": "Битые авто в Королеве: где купить, цены, оценка и ремонт", "i": "📁", "c": null}]