[{"s": "gde-posmotret-nomer-shassi-avtomobilya", "t": "Где посмотреть номер шасси автомобиля: 7 проверенных способов", "i": "📄", "c": "registratsiya-i-dokumenty"}, {"s": "gde-proizvoditsya-aurus-avtomobil", "t": "Где производят Aurus: заводы, технологии и локализация в 2026 году", "i": "🤝", "c": "pokupka-i-prodazha"}, {"s": "gde-primenyaetsya-kislotnyj-grunt", "t": "Кислотный грунт: где и как применяется в авторемонте | Полный гайд", "i": "🎨", "c": "kuzov-i-okraska"}, {"s": "gde-prodat-bu-zapchasti-dlya-avtomobilya", "t": "Где продать б/у запчасти для авто: 10 лучших способов 2026", "i": "🤝", "c": "pokupka-i-prodazha"}, {"s": "gde-pokupat-mashiny-v-forza-khorajzen-4", "t": "Где купить машины в Forza Horizon 4: лучшие способы и советы 2026", "i": "📁", "c": "drugoe"}, {"s": "gde-posmotret-zalog-na-mashinu-onlajn", "t": "Как проверить залог на машину онлайн: все способы 2026", "i": "📄", "c": "registratsiya-i-dokumenty"}, {"s": "gde-posmotret-skolko-loshadej-v-mashine", "t": "Как узнать количество лошадиных сил в машине — 5 проверенных способов", "i": "📄", "c": "registratsiya-i-dokumenty"}, {"s": "gde-podozhdat-prileta-v-sheremetevo-na-mashine-terminal-v", "t": "Где ждать прилёта в Шереметьево на машине: терминал В (2026)", "i": "🗺️", "c": "puteshestviya-i-dorogi"}, {"s": "gde-pobyvat-na-altae-na-mashine-letom", "t": "Алтай на машине летом: 10 маршрутов для автопутешественников 2026", "i": "🗺️", "c": "puteshestviya-i-dorogi"}, {"s": "gde-proizvodyat-lamborgini-strana", "t": "Где производят Lamborghini: страна, заводы и особенности сборки", "i": "🤝", "c": "pokupka-i-prodazha"}, {"s": "gde-proverit-osago-na-podlinnost-rsa-polis", "t": "Как проверить ОСАГО на подлинность через РСА: пошаговая инструкция 2026", "i": "📄", "c": "registratsiya-i-dokumenty"}, {"s": "gde-posmotret-tsvet-mashiny", "t": "Где посмотреть цвет машины: 7 проверенных способов (2026)", "i": "📄", "c": "registratsiya-i-dokumenty"}, {"s": "gde-perekupy-ishchut-avtomobili", "t": "Где перекупы ищут автомобили в 2026 году: секретные источники", "i": "🤝", "c": "pokupka-i-prodazha"}, {"s": "gde-posmotret-nomer-zapchasti-na-avtomobil", "t": "Где найти номер запчасти на автомобиль: 7 проверенных способов", "i": "🔧", "c": "remont-dvigatelya"}, {"s": "gde-posmotret-elektronnuyu-strakhovku", "t": "Где посмотреть электронную страховку ОСАГО: 7 проверенных способов", "i": "📄", "c": "registratsiya-i-dokumenty"}, {"s": "gde-po-pravilam-dolzhno-stoyat-detskoe-kreslo-v-mashine", "t": "Где ставить детское кресло в машине по ПДД 2026: правила и штрафы", "i": "👶", "c": "detskaya-bezopasnost"}, {"s": "gde-proizvoditsya-avtomobil-moskvich", "t": "Где производят «Москвич»: заводы и география сборки в 2026 году", "i": "🤝", "c": "pokupka-i-prodazha"}, {"s": "gde-posmotret-avtomobili-s-probegom", "t": "Где купить автомобиль с пробегом: 10 проверенных способов 2026", "i": "🤝", "c": "pokupka-i-prodazha"}, {"s": "gde-posmotret-datu-proizvodstva-avtomobilya", "t": "Где посмотреть дату производства авто: 7 проверенных способов", "i": "📄", "c": "registratsiya-i-dokumenty"}, {"s": "gde-posmotret-nalog-na-avtomobil-na-gosuslugakh", "t": "Как проверить налог на автомобиль через Госуслуги в 2026 году", "i": "📄", "c": "registratsiya-i-dokumenty"}, {"s": "gde-pokrasit-avto-v-spb-kachestvenno", "t": "Где покрасить авто в СПб качественно: ТОП-10 сервисов 2026", "i": "🎨", "c": "kuzov-i-okraska"}, {"s": "gde-proshche-sdat-na-prava-v-kakoj-oblasti", "t": "Где проще сдать на права в 2026 году: рейтинг регионов России", "i": "📄", "c": "registratsiya-i-dokumenty"}, {"s": "gde-prodayut-transpondery-dlya-platnykh-dorog", "t": "Где купить транспондер для платных дорог в 2026 году: ТОП-10 мест", "i": "🗺️", "c": "puteshestviya-i-dorogi"}, {"s": "gde-posmotret-gruzopodemnost-avtomobilya-v-pts", "t": "Где посмотреть грузоподъёмность авто в ПТС: инструкция 2026", "i": "📄", "c": "registratsiya-i-dokumenty"}, {"s": "gde-pishetsya-nomer-epts", "t": "Где пишется номер ЭПТС в 2026 году: где искать и как проверить", "i": "📄", "c": "registratsiya-i-dokumenty"}, {"s": "gde-priparkovatsya-vozle-paveletskogo-vokzala", "t": "Где припарковаться у Павелецкого вокзала: платные и бесплатные зоны", "i": "🗺️", "c": "puteshestviya-i-dorogi"}, {"s": "gde-posmotret-svoj-epts", "t": "Где посмотреть свой ЭПТС: все способы проверки статуса", "i": "📄", "c": "registratsiya-i-dokumenty"}, {"s": "gde-posmotret-vin-kod-avtomobilya-v-tekhpasporte", "t": "Где смотреть VIN код в техпаспорте: подробный гид", "i": "📁", "c": null}, {"s": "gde-posmotret-ekologicheskij-klass-transportnogo-sredstva", "t": "Где посмотреть экологический класс автомобиля: все способы проверки", "i": "📄", "c": "registratsiya-i-dokumenty"}, {"s": "gde-priparkovatsya-u-ermitazha", "t": "Где припарковаться у Эрмитажа: все парковки и цены 2026", "i": "🗺️", "c": "puteshestviya-i-dorogi"}, {"s": "gde-priparkovatsya-u-tretyakovskoj-galerei", "t": "Где припарковаться у Третьяковской галереи: парковки и цены", "i": "🗺️", "c": "puteshestviya-i-dorogi"}, {"s": "gde-prodat-avtomobil-s-probegom-cherez-internet-besplatno", "t": "Где бесплатно продать авто с пробегом: ТОП площадок", "i": "🤝", "c": "pokupka-i-prodazha"}, {"s": "gde-proverit-epts-elektronnyj-pts-na-avtomobil", "t": "Где проверить ЭПТС: официальные сервисы и базы данных", "i": "📄", "c": "registratsiya-i-dokumenty"}, {"s": "gde-posmotret-kakaya-komplektatsiya-u-mashiny", "t": "Как узнать комплектацию авто: все способы проверки", "i": "🤝", "c": "pokupka-i-prodazha"}, {"s": "gde-posmotret-otts-na-svoj-avtomobil", "t": "Где посмотреть ОТТС на автомобиль: 6 способов проверки", "i": "📄", "c": "registratsiya-i-dokumenty"}, {"s": "gde-posmotret-raskhod-topliva-avtomobilya-v-dokumentakh", "t": "Где посмотреть расход топлива: документы и методы", "i": "📄", "c": "registratsiya-i-dokumenty"}, {"s": "gde-posmotret-zapis-v-gibdd-cherez-gosuslugi", "t": "Где посмотреть запись в ГИБДД через Госуслуги: пошаговая инструкция", "i": "📄", "c": "registratsiya-i-dokumenty"}, {"s": "gde-prodayut-mashiny-otobrannye-sudebnymi-pristavami", "t": "Где продают машины отобранные судебными приставами: гид по аукционам", "i": "🤝", "c": "pokupka-i-prodazha"}, {"s": "gde-posmotret-nakhoditsya-li-mashina-v-zaloge-u-banka", "t": "Как проверить машину на залог: базы данных и риски", "i": "🤝", "c": "pokupka-i-prodazha"}, {"s": "gde-posmotret-elektronnuyu-strakhovku-na-mashinu-osago", "t": "Где посмотреть электронную страховку ОСАГО: поиск и проверка", "i": "📄", "c": "registratsiya-i-dokumenty"}, {"s": "gde-plyus-i-minus-na-kolonkakh-avtomobilnykh", "t": "Где плюс и минус на колонках авто: схемы и фото", "i": "⚡", "c": "elektrika-i-svet"}, {"s": "gde-priparkovatsya-u-kurskogo-vokzala", "t": "Где припарковаться у Курского вокзала: парковки, цены и тарифы", "i": "🗺️", "c": "puteshestviya-i-dorogi"}, {"s": "gde-posmotret-komplektatsiyu-avtomobilya-v-pts", "t": "Где в ПТС посмотреть комплектацию: расшифровка кодов и VIN", "i": "📄", "c": "registratsiya-i-dokumenty"}, {"s": "gde-priparkovatsya-u-moskvariuma-na-vdnkh", "t": "Где припарковаться у Москвариума на ВДНХ: гид по парковкам", "i": "🗺️", "c": "puteshestviya-i-dorogi"}, {"s": "gde-priparkovatsya-u-paveletskogo-vokzala-besplatno", "t": "Где припарковаться у Павелецкого вокзала бесплатно: парковки и правила", "i": "📁", "c": null}, {"s": "gde-perekupy-berut-mashiny", "t": "Где перекупы берут машины: схемы поиска и источники авто", "i": "🤝", "c": "pokupka-i-prodazha"}, {"s": "gde-posmotret-epts-svoego-avtomobilya", "t": "Где посмотреть ЭПТС: 5 способов узнать данные онлайн", "i": "📄", "c": "registratsiya-i-dokumenty"}, {"s": "gde-posmotret-skolko-loshadinykh-sil-u-mashiny", "t": "Где посмотреть лошадиные силы: 7 способов узнать мощность авто", "i": "📄", "c": "registratsiya-i-dokumenty"}, {"s": "gde-pokupat-zapchasti-na-kitajskie-avto", "t": "Где покупать запчасти на китайские авто: надежные поставщики и советы", "i": "🔧", "c": "remont-dvigatelya"}, {"s": "gde-posmotret-dannye-epts", "t": "Где посмотреть данные ЭПТС: поиск по номеру и VIN", "i": "📄", "c": "registratsiya-i-dokumenty"}, {"s": "gde-posmotret-vin-kod", "t": "Где посмотреть VIN-код: 15 мест в автомобиле и документах", "i": "📄", "c": "registratsiya-i-dokumenty"}, {"s": "gde-postavit-pech-v-garazhe", "t": "Где поставить печь в гараже: схемы, нормы и безопасность", "i": "🏠", "c": "garazh-i-instrument"}, {"s": "gde-primenyayut-uglekislotnye-ognetushiteli", "t": "Где применяют углекислотные огнетушители: сферы и правила", "i": "🚑", "c": "bezopasnost-i-zdorove"}, {"s": "gde-pishetsya-probeg-avtomobilya", "t": "Где пишется пробег автомобиля: места в ПТС, СТС и ДКП", "i": "📄", "c": "registratsiya-i-dokumenty"}, {"s": "gde-priparkovatsya-u-bolshogo-teatra", "t": "Где припарковаться у Большого театра: парковки и цены", "i": "🗺️", "c": "puteshestviya-i-dorogi"}, {"s": "gde-priparkovatsya-u-parka-gorkogo", "t": "Где припарковаться у парка Горького: платные и бесплатные зоны", "i": "🗺️", "c": "puteshestviya-i-dorogi"}, {"s": "gde-poluchit-diagnosticheskuyu-kartu-na-avtomobil-dlya-postanovki-na-uchet-v-gibdd-cherez-gosuslugi", "t": "Где получить диагностическую карту для ГИБДД: актуально 2026", "i": "📄", "c": "registratsiya-i-dokumenty"}, {"s": "gde-parkovatsya-u-moskvariuma", "t": "Где парковаться у Москвариума: цены, схемы и секреты 2026", "i": "🗺️", "c": "puteshestviya-i-dorogi"}, {"s": "gde-postavit-mashinu-v-aeroportu-sheremetevo", "t": "Где оставить машину в Шереметьево: цены парковок и секреты экономии", "i": "🗺️", "c": "puteshestviya-i-dorogi"}, {"s": "gde-postavit-mashinu-u-paveletskogo-vokzala", "t": "Где оставить машину у Павелецкого вокзала: парковки и цены", "i": "🗺️", "c": "puteshestviya-i-dorogi"}, {"s": "gde-pravorulnye-mashiny-strany", "t": "Где праворульные машины: страны и правила ввоза", "i": "📁", "c": null}, {"s": "gde-poluchit-spravku-ob-utilizatsii-avtomobilya-bez-avtomobilya", "t": "Справка об утилизации авто без машины: законные способы", "i": "📄", "c": "registratsiya-i-dokumenty"}, {"s": "gde-posmotret-nomer-kuzova-avtomobilya-v-pts", "t": "Где в ПТС посмотреть номер кузова: расшифровка и проверка", "i": "📄", "c": "registratsiya-i-dokumenty"}, {"s": "gde-posmotret-snyat-li-avtomobil-s-ucheta-v-gibdd", "t": "Где посмотреть, снят ли автомобиль с учета в ГИБДД: способы проверки", "i": "📄", "c": "registratsiya-i-dokumenty"}, {"s": "gde-priparkovat-mashinu-na-kazanskom-vokzale", "t": "Где припарковать машину на Казанском вокзале: цены и схема", "i": "🗺️", "c": "puteshestviya-i-dorogi"}, {"s": "gde-proizvodyat-avtomobili-gac", "t": "Где производят автомобили GAC: заводы в Китае и России", "i": "🤝", "c": "pokupka-i-prodazha"}, {"s": "gde-posmotret-kem-vydan-pts-na-mashinu", "t": "Кем выдан ПТС: где найти информацию и что делать", "i": "📄", "c": "registratsiya-i-dokumenty"}, {"s": "gde-postavit-mashinu-na-vdnkh-besplatno", "t": "Где поставить машину на ВДНХ бесплатно: парковки и перехваты", "i": "🗺️", "c": "puteshestviya-i-dorogi"}, {"s": "gde-posmotret-razmer-shin-na-avto", "t": "Где посмотреть размер шин на авто: 5 проверенных мест", "i": "🛠️", "c": "aksessuary-i-tyuning"}, {"s": "gde-priparkovatsya-u-mariinskogo-teatra", "t": "Где припарковаться у Мариинского театра: парковки, цены и советы", "i": "🗺️", "c": "puteshestviya-i-dorogi"}]