[{"s": "hiace-perevod-s-anglijskogo-na-russkij", "t": "Toyota Hiace: перевод названия и расшифровка модели", "i": "🤝", "c": "pokupka-i-prodazha"}, {"s": "hisense-stiralnaya-mashina-otzyvy-masterov-po-remontu", "t": "Hisense стиральные машины: отзывы мастеров по ремонту 2026", "i": "🔧", "c": "remont-dvigatelya"}, {"s": "hiphi-z-razgon-do-100", "t": "HiPhi Z разгон до 100 км/ч: тест динамики и характеристики", "i": "🛠️", "c": "aksessuary-i-tyuning"}, {"s": "hiphi-z-skolko-loshadej", "t": "HiPhi Z: сколько лошадей и характеристик у электрокара", "i": "🛠️", "c": "aksessuary-i-tyuning"}, {"s": "hifi-z-kitajskij-avto", "t": "Китайский Hi-Fi авто: выбор, установка и настройка звука", "i": "🛠️", "c": "aksessuary-i-tyuning"}, {"s": "hill-start-assist-chto-eto", "t": "Hill Start Assist: что это такое, как работает и зачем нужен", "i": "🚑", "c": "bezopasnost-i-zdorove"}, {"s": "high-beam-perevod-na-russkij-s-anglijskogo", "t": "High Beam перевод: значение на русском и обозначение в авто", "i": "🛠️", "c": "aksessuary-i-tyuning"}, {"s": "hispano-suiza-j12-t-68-kupit-model", "t": "Hispano Suiza J12 T 68: купить модель, цена и обзор", "i": "🛠️", "c": "aksessuary-i-tyuning"}, {"s": "hino-chto-za-marka-avtomobilya", "t": "Hino: что за марка автомобиля? История, модели и особенности", "i": "📁", "c": "drugoe"}, {"s": "high-power-jump-starter-kupit", "t": "Где купить High Power Jump Starter: рейтинг и советы", "i": "🛠️", "c": "aksessuary-i-tyuning"}, {"s": "hisense-chto-za-firma", "t": "Hisense что за фирма: история, качество и обзоры", "i": "📁", "c": null}, {"s": "hi-stiralnaya-mashina-otzyvy", "t": "HI стиральные машины: отзывы владельцев, характеристики и поломки", "i": "📁", "c": "drugoe"}, {"s": "hikan-studio-problemy-s-mashinoj", "t": "Проблемы с машиной Hikvision: диагностика и решения", "i": "📁", "c": "drugoe"}, {"s": "hino-kto-proizvoditel-strana", "t": "Hino: производитель, страна и история бренда грузовиков", "i": "📁", "c": "drugoe"}]